AUTHORS
ChangeLog
Dockerfile
LICENSE
Makefile
README.md
demo.gif
requirements.txt
setup.cfg
setup.py
open_cli/__init__.py
open_cli/cli.py
open_cli/completer.py
open_cli/formatter.py
open_cli/help.py
open_cli/main.py
open_cli/parser.py
opencli.egg-info/PKG-INFO
opencli.egg-info/SOURCES.txt
opencli.egg-info/dependency_links.txt
opencli.egg-info/entry_points.txt
opencli.egg-info/not-zip-safe
opencli.egg-info/pbr.json
opencli.egg-info/requires.txt
opencli.egg-info/top_level.txt