Metadata-Version: 1.1
Name: opencli
Version: 0.0.9
Summary: Generate client based on OpenAPI Specification and wrap it in a command line interface
Home-page: https://github.com/sharbov/open-cli
Author: Shay Arbov
Author-email: shay.arbov@gmail.com
License: MIT
Platform: UNKNOWN
Classifier: Environment :: Console
Classifier: Intended Audience :: Information Technology
Classifier: Intended Audience :: System Administrators
Classifier: Operating System :: POSIX :: Linux
Classifier: Programming Language :: Python
Classifier: Programming Language :: Python :: 3
Classifier: Programming Language :: Python :: 3.6
